plothist_utils/__init__.py
plothist_utils/_version.py
plothist_utils/_version.pyi
plothist_utils/get_dummy_data.py
plothist_utils/data/dummy_data.csv
plothist_utils/fonts/latinmodernmath/LICENSE_LMMath
plothist_utils/fonts/latinmodernmath/latinmodern-math.otf
plothist_utils/fonts/latinmodernroman/LICENSE_LMRoman
plothist_utils/fonts/latinmodernroman/lmroman10-bold.otf
plothist_utils/fonts/latinmodernroman/lmroman10-bolditalic.otf
plothist_utils/fonts/latinmodernroman/lmroman10-italic.otf
plothist_utils/fonts/latinmodernroman/lmroman10-regular.otf
plothist_utils/fonts/latinmodernroman/lmroman12-bold.otf
plothist_utils/fonts/latinmodernroman/lmroman12-italic.otf
plothist_utils/fonts/latinmodernroman/lmroman12-regular.otf
plothist_utils/fonts/latinmodernroman/lmroman17-regular.otf
plothist_utils/fonts/latinmodernroman/lmroman5-bold.otf
plothist_utils/fonts/latinmodernroman/lmroman5-regular.otf
plothist_utils/fonts/latinmodernroman/lmroman6-bold.otf
plothist_utils/fonts/latinmodernroman/lmroman6-regular.otf
plothist_utils/fonts/latinmodernroman/lmroman7-bold.otf
plothist_utils/fonts/latinmodernroman/lmroman7-italic.otf
plothist_utils/fonts/latinmodernroman/lmroman7-regular.otf
plothist_utils/fonts/latinmodernroman/lmroman8-bold.otf
plothist_utils/fonts/latinmodernroman/lmroman8-italic.otf
plothist_utils/fonts/latinmodernroman/lmroman8-regular.otf
plothist_utils/fonts/latinmodernroman/lmroman9-bold.otf
plothist_utils/fonts/latinmodernroman/lmroman9-italic.otf
plothist_utils/fonts/latinmodernroman/lmroman9-regular.otf
plothist_utils/fonts/latinmodernroman/lmromancaps10-oblique.otf
plothist_utils/fonts/latinmodernroman/lmromancaps10-regular.otf
plothist_utils/fonts/latinmodernroman/lmromandemi10-oblique.otf
plothist_utils/fonts/latinmodernroman/lmromandemi10-regular.otf
plothist_utils/fonts/latinmodernroman/lmromandunh10-oblique.otf
plothist_utils/fonts/latinmodernroman/lmromandunh10-regular.otf
plothist_utils/fonts/latinmodernroman/lmromanslant10-bold.otf
plothist_utils-0.0.1.dist-info/METADATA
plothist_utils-0.0.1.dist-info/WHEEL
plothist_utils-0.0.1.dist-info/licenses/AUTHORS.md
plothist_utils-0.0.1.dist-info/licenses/LICENSE
plothist_utils-0.0.1.dist-info/RECORD
