Metadata-Version: 2.4
Name: plothist_utils
Version: 0.0.1
Summary: Utilities for the plothist package
Project-URL: Homepage, https://github.com/0ctagon/plothist_utils
Project-URL: Documentation, https://plothist.readthedocs.io/
Project-URL: Bug Tracker, https://github.com/0ctagon/plothist_utils/issues
Author-email: Cyrille Praz <cyrraz.code@protonmail.com>, Tristan Fillinger <tristan.github@gmail.com>
License-File: AUTHORS.md
License-File: LICENSE
Requires-Python: >=3.9
Requires-Dist: numpy>=1.14.5
